amis/__init__.py
amis/components.py
amis/constants.py
amis/templates/app.jinja2
amis/templates/page.jinja2
amis/types.py
amis_py_model-1.0.0.dist-info/LICENSE
amis_py_model-1.0.0.dist-info/METADATA
amis_py_model-1.0.0.dist-info/WHEEL
amis_py_model-1.0.0.dist-info/RECORD
